[
    {
        "university_name": "LMU - University of Munich",
        "university_link": "https://www.studycheck.de/hochschulen/lmu-muenchen",
        "program_name": "Egyptology and Coptology",
        "program_link": "https://www.studycheck.de/studium/aegyptologie/lmu-muenchen-4781",
        "full_name": "Egyptology and Coptology (BA)",
        "description": "Course details\n\n\nThe \"Egyptology and Coptology\" Course at the State \"LMU - University of Munich\" Has a Standard Period of 6 Semesters and Ends with the Degree \"Bachelor of Arts\".The Course is located in Munich.The course is offered as a full-time course.The Course Has Been Rated 4 Times in Total so far.It has received an Average of 4.0 Stars and is Therefore Above the University's Average Rating (3.8 Stars, 3556 ratings in the rating).The Categories of Lecturers, Access to Literature and Course Content Were Rated Particularly Well.\n\nFor universities: Create a Study Profile and Adapt the text.\n\n\n\n\n\nDual Subject Bachelor - Major (120 CP)\n\n\n\n\n\n\n\n\nDual Subject Bachelor - Major (120 CP)\n6 semesters\n\n\n\n\n\n\nDual Subject Bachelor - Major (120 CP)\n6 semesters\n\n\n\n\n\nEvaluation\n\n\n\n\n\n\n\n\n4.0\n\n\n\n\n4 reviews\n\n\n\n\n\n100%\nrecommendation\n\n\n\n\n\n\n\nReviews\n\n\n\n4 testimonials\n\n\n\n\n\n\n\n\nRecommendation\n\n\n100%\n\n\n\n\nStandard period of study\n\n\n6 semesters\n\n\n\n\n\n\nStart of Studies\n\nWinter semester\n\n\n\n\nDiploma\n\nBachelor of Arts\n\n\n\n\n\nLanguages \u200b\u200bof Instruction\n\nGerman\n\n\n\nLocations\nMunich",
        "rating": "4.0",
        "information": {
            "Evaluation": "4.0\n                                            \n\n\n\n                                                    4 reviews\n                                                \n\n\n\n\n100% \nrecommendation",
            "Reviews": "4 testimonials",
            "Recommendation": "100%",
            "Standard_period_of_study": "6 semesters",
            "Start_of_studies": "Winter semester",
            "Diploma": "Bachelor of Arts",
            "Languages_\u200b\u200bof_instruction": "German",
            "Locations": "Munich"
        }
    },
    {
        "university_name": "LMU - University of Munich",
        "university_link": "https://www.studycheck.de/hochschulen/lmu-muenchen",
        "program_name": "Egyptology and Coptology",
        "program_link": "https://www.studycheck.de/studium/aegyptologie/lmu-muenchen-10601",
        "full_name": "Egyptology and Coptology (MA)",
        "description": "Course details\n\n\nThe \"Egyptology and Coptology\" Course at the State \"LMU - University of Munich\" Has a Standard Period of 4 Semesters and Ends with the Degree \"Master of Arts\".The Course is located in Munich.The course is offered as a full-time course.The Course Has Been Rated 2 Times So Far.It has received an average of 4.2 Stars and is Therefore above the University's Average Rating (3.8 stars, 3556 ratings in the rating).The Categories of Course Content, Equipment and Access to Literature Were Rated Particularly Well.\n\nFor universities: Create a Study Profile and Adapt the text.\n\n\n\n\n\nSingle-Subject Master (120cp)\n\n\n\n\n\n\n\n\nSingle-Subject Master (120cp)\n4 semesters\n\n\n\n\n\n\nSingle-Subject Master (120cp)\n4 semesters\n\n\n\n\n\nEvaluation\n\n\n\n\n\n\n\n\n4.2\n\n\n\n\n2 reviews\n\n\n\n\n\n100%\nrecommendation\n\n\n\n\n\n\n\nReviews\n\n\n\n2 reviews\n\n\n\n\n\n\n\n\nRecommendation\n\n\n100%\n\n\n\n\nStandard period of study\n\n\n4 semesters\n\n\n\n\n\n\nStart of Studies\n\nWinter semester\n\n\n\n\nDiploma\n\nMaster of Arts\n\n\n\n\n\nLanguages \u200b\u200bof Instruction\n\nGerman\n\n\n\nLocations\nMunich",
        "rating": "4.2",
        "information": {
            "Evaluation": "4.2\n                                            \n\n\n\n                                                    2 reviews\n                                                \n\n\n\n\n100% \nrecommendation",
            "Reviews": "2 reviews",
            "Recommendation": "100%",
            "Standard_period_of_study": "4 semesters",
            "Start_of_studies": "Winter semester",
            "Diploma": "Master of Arts",
            "Languages_\u200b\u200bof_instruction": "German",
            "Locations": "Munich"
        }
    }
]